MANIFEST.in
setup.cfg
setup.py
pygeosearch/__init__.py
pygeosearch/geohashsearch.py
pygeosearch/geosearch.py
pygeosearch/rw_lock.py
pygeosearch/shared_redis.py
pygeosearch.egg-info/PKG-INFO
pygeosearch.egg-info/SOURCES.txt
pygeosearch.egg-info/dependency_links.txt
pygeosearch.egg-info/requires.txt
pygeosearch.egg-info/top_level.txt