Metadata-Version: 1.1
Name: pygeosearch
Version: 0.0.2
Summary: Geo search using redis
Home-page: https://github.com/shipunyc/pygeosearch
Author: Pu Shi
Author-email: mr.pu.shi@gmail.com
License: UNKNOWN
Platform: UNKNOWN
Classifier: Environment :: Console
Classifier: Intended Audience :: Developers
Classifier: Operating System :: OS Independent
Classifier: Programming Language :: Python
Classifier: Programming Language :: Python :: 2.7
